paynter/__init__.py
paynter/blendModes.py
paynter/brush.py
paynter/color.py
paynter/config.py
paynter/image.py
paynter/layer.py
paynter/paynter.py
paynter/utils.py
paynter-0.1.4.dist-info/LICENSE
paynter-0.1.4.dist-info/METADATA
paynter-0.1.4.dist-info/WHEEL
paynter-0.1.4.dist-info/top_level.txt
paynter-0.1.4.dist-info/RECORD
