Metadata-Version: 2.1
Name: paynter
Version: 0.1.4
Summary: PaYnter is a Python Library that let you procedurally generate images with handy features that emulates what you can find in any image editing software like Photoshop, GIMP, Krita, and similars.
Home-page: https://github.com/elkiwy/paynter
Author: Stefano Bertoli
Author-email: elkiwydev@gmail.com
License: UNKNOWN
Platform: UNKNOWN
Classifier: Programming Language :: Python :: 3
Classifier: License :: OSI Approved :: MIT License
Classifier: Operating System :: OS Independent
